setup.py
har/__init__.py
har/harparser.py
har.egg-info/PKG-INFO
har.egg-info/SOURCES.txt
har.egg-info/dependency_links.txt
har.egg-info/top_level.txt